support_toolbox/__init__.py
support_toolbox/clear_user_layer.py
support_toolbox/delete_users.py
support_toolbox/deploy_browse_card.py
support_toolbox/deploy_ctk_service_account.py
support_toolbox/deploy_integrations.py
support_toolbox/deploy_pi.py
support_toolbox/main.py
support_toolbox/onboard_ctk_orgs.py
support_toolbox/revert_soft_delete.py
support_toolbox/update_saml.py
support_toolbox/api/__init__.py
support_toolbox/api/dataset.py
support_toolbox/api/entitlements.py
support_toolbox/api/file.py
support_toolbox/api/org.py
support_toolbox/api/project.py
support_toolbox/api/service_account.py
support_toolbox/api/site.py
support_toolbox/api/user.py
support_toolbox/app_handler/__init__.py
support_toolbox/app_handler/app.py
support_toolbox/app_handler/app_version.py
support_toolbox/app_handler/auto_updater.py
support_toolbox/app_handler/token_manager.py
support_toolbox/utils/__init__.py
support_toolbox/utils/api_url.py
support_toolbox/utils/csv_to_iris.py
support_toolbox/utils/metrics.py
support_toolbox/utils/resource_type.py
support_toolbox/utils/saml_parser.py
support_toolbox-0.9.4.dist-info/METADATA
support_toolbox-0.9.4.dist-info/WHEEL
support_toolbox-0.9.4.dist-info/entry_points.txt
support_toolbox-0.9.4.dist-info/top_level.txt
support_toolbox-0.9.4.dist-info/RECORD
