Metadata-Version: 2.1
Name: support-toolbox
Version: 0.9.4
Summary: A suite of CLI tools for the data.world support team
Home-page: https://github.com/datadotworld/support-toolbox/tree/main
Author: Jack Compton
Author-email: jack.compton@data.world
Requires-Dist: certifi ==2023.7.22
Requires-Dist: charset-normalizer ==3.2.0
Requires-Dist: defusedxml ==0.7.1
Requires-Dist: idna ==3.4
Requires-Dist: jira ==3.5.2
Requires-Dist: oauthlib ==3.2.2
Requires-Dist: packaging ==23.1
Requires-Dist: requests ==2.31.0
Requires-Dist: requests-oauthlib ==1.3.1
Requires-Dist: requests-toolbelt ==1.0.0
Requires-Dist: typing-extensions ==4.7.1
Requires-Dist: urllib3 ==2.0.4
